{
  "source": "openalex",
  "openalex_id": "https://openalex.org/W4412745982",
  "title": "Immune evasion in cancer: mechanisms and cutting-edge therapeutic approaches",
  "publication_year": 2025,
  "publication_date": "2025-07-30",
  "type": "review",
  "citation_count": 36,
  "cited_by_count": 36,
  "is_oa": true,
  "oa_status": "gold",
  "oa_url": "https://www.nature.com/articles/s41392-025-02280-1.pdf",
  "authors": [
    {
      "id": "https://openalex.org/A5102792062",
      "display_name": "Muhammad Tufail",
      "orcid": "https://orcid.org/0000-0003-3442-7216",
      "institutions": [
        {
          "id": "https://openalex.org/I139660479",
          "display_name": "Central South University",
          "country": "China",
          "type": "education",
          "ror_id": "https://ror.org/00f1zfq44",
          "status": "active",
          "types": [
            "education",
            "funder"
          ],
          "established": 2000,
          "names": [
            {
              "lang": null,
              "types": [
                "acronym"
              ],
              "value": "CSU"
            },
            {
              "lang": "en",
              "types": [
                "ror_display",
                "label"
              ],
              "value": "Central South University"
            },
            {
              "lang": "zh",
              "types": [
                "label"
              ],
              "value": "中南大学"
            }
          ],
          "locations": [
            {
              "geonames_details": {
                "continent_code": "AS",
                "continent_name": "Asia",
                "country_code": "CN",
                "country_name": "China",
                "country_subdivision_code": "HN",
                "country_subdivision_name": "Hunan",
                "lat": 28.19874,
                "lng": 112.97087,
                "name": "Changsha"
              },
              "geonames_id": 1815577
            }
          ],
          "country_code": "CN",
          "city": "Changsha",
          "latitude": 28.19874,
          "longitude": 112.97087,
          "links": [
            {
              "type": "website",
              "value": "https://www.csu.edu.cn"
            },
            {
              "type": "wikipedia",
              "value": "http://en.wikipedia.org/wiki/Central_South_University"
            }
          ],
          "website": "https://www.csu.edu.cn",
          "external_ids": [
            {
              "all": [
                "501100002822",
                "501100012476",
                "501100012486"
              ],
              "preferred": null,
              "type": "fundref"
            },
            {
              "all": [
                "grid.216417.7"
              ],
              "preferred": "grid.216417.7",
              "type": "grid"
            },
            {
              "all": [
                "0000 0001 0379 7164"
              ],
              "preferred": null,
              "type": "isni"
            },
            {
              "all": [
                "Q5061828"
              ],
              "preferred": null,
              "type": "wikidata"
            }
          ],
          "grid_id": "grid.216417.7",
          "relationships": [
            {
              "label": "State Key Laboratory of High Performance Complex Manufacturing",
              "type": "child",
              "id": "https://ror.org/04xjtqb36"
            },
            {
              "label": "State Key Laboratory of Powder Metallurgy",
              "type": "child",
              "id": "https://ror.org/04r12t513"
            },
            {
              "label": "Haikou City People's Hospital",
              "type": "related",
              "id": "https://ror.org/00ha5jx35"
            },
            {
              "label": "Second Xiangya Hospital of Central South University",
              "type": "related",
              "id": "https://ror.org/053v2gh09"
            },
            {
              "label": "Xiangya Hospital Central South University",
              "type": "related",
              "id": "https://ror.org/05c1yfj14"
            },
            {
              "label": "Zhuzhou Central Hospital",
              "type": "related",
              "id": "https://ror.org/03prq2784"
            }
          ],
          "domains": [
            "csu.edu.cn"
          ]
        },
        {
          "id": "https://openalex.org/I4210159865",
          "display_name": "Xiangya Hospital Central South University",
          "country": "China",
          "type": "healthcare",
          "ror_id": "https://ror.org/05c1yfj14",
          "status": "active",
          "types": [
            "funder",
            "healthcare"
          ],
          "established": 1906,
          "names": [
            {
              "lang": "en",
              "types": [
                "ror_display",
                "label"
              ],
              "value": "Xiangya Hospital Central South University"
            },
            {
              "lang": "zh",
              "types": [
                "label"
              ],
              "value": "中南大学湘雅医院"
            }
          ],
          "locations": [
            {
              "geonames_details": {
                "continent_code": "AS",
                "continent_name": "Asia",
                "country_code": "CN",
                "country_name": "China",
                "country_subdivision_code": "HN",
                "country_subdivision_name": "Hunan",
                "lat": 28.19874,
                "lng": 112.97087,
                "name": "Changsha"
              },
              "geonames_id": 1815577
            }
          ],
          "country_code": "CN",
          "city": "Changsha",
          "latitude": 28.19874,
          "longitude": 112.97087,
          "links": [
            {
              "type": "website",
              "value": "http://www.xiangya.com.cn/web/#"
            }
          ],
          "website": "http://www.xiangya.com.cn/web/#",
          "external_ids": [
            {
              "all": [
                "501100011790"
              ],
              "preferred": "501100011790",
              "type": "fundref"
            },
            {
              "all": [
                "grid.452223.0"
              ],
              "preferred": "grid.452223.0",
              "type": "grid"
            },
            {
              "all": [
                "0000 0004 1757 7615"
              ],
              "preferred": null,
              "type": "isni"
            }
          ],
          "fundref_id": "501100011790",
          "grid_id": "grid.452223.0",
          "relationships": [
            {
              "label": "Central South University",
              "type": "related",
              "id": "https://ror.org/00f1zfq44"
            }
          ],
          "domains": []
        }
      ],
      "position": "first"
    },
    {
      "id": "https://openalex.org/A5070383983",
      "display_name": "Canhua Jiang",
      "orcid": "https://orcid.org/0000-0002-8133-1981",
      "institutions": [
        {
          "id": "https://openalex.org/I139660479",
          "display_name": "Central South University",
          "country": "China",
          "type": "education",
          "ror_id": "https://ror.org/00f1zfq44",
          "status": "active",
          "types": [
            "education",
            "funder"
          ],
          "established": 2000,
          "names": [
            {
              "lang": null,
              "types": [
                "acronym"
              ],
              "value": "CSU"
            },
            {
              "lang": "en",
              "types": [
                "ror_display",
                "label"
              ],
              "value": "Central South University"
            },
            {
              "lang": "zh",
              "types": [
                "label"
              ],
              "value": "中南大学"
            }
          ],
          "locations": [
            {
              "geonames_details": {
                "continent_code": "AS",
                "continent_name": "Asia",
                "country_code": "CN",
                "country_name": "China",
                "country_subdivision_code": "HN",
                "country_subdivision_name": "Hunan",
                "lat": 28.19874,
                "lng": 112.97087,
                "name": "Changsha"
              },
              "geonames_id": 1815577
            }
          ],
          "country_code": "CN",
          "city": "Changsha",
          "latitude": 28.19874,
          "longitude": 112.97087,
          "links": [
            {
              "type": "website",
              "value": "https://www.csu.edu.cn"
            },
            {
              "type": "wikipedia",
              "value": "http://en.wikipedia.org/wiki/Central_South_University"
            }
          ],
          "website": "https://www.csu.edu.cn",
          "external_ids": [
            {
              "all": [
                "501100002822",
                "501100012476",
                "501100012486"
              ],
              "preferred": null,
              "type": "fundref"
            },
            {
              "all": [
                "grid.216417.7"
              ],
              "preferred": "grid.216417.7",
              "type": "grid"
            },
            {
              "all": [
                "0000 0001 0379 7164"
              ],
              "preferred": null,
              "type": "isni"
            },
            {
              "all": [
                "Q5061828"
              ],
              "preferred": null,
              "type": "wikidata"
            }
          ],
          "grid_id": "grid.216417.7",
          "relationships": [
            {
              "label": "State Key Laboratory of High Performance Complex Manufacturing",
              "type": "child",
              "id": "https://ror.org/04xjtqb36"
            },
            {
              "label": "State Key Laboratory of Powder Metallurgy",
              "type": "child",
              "id": "https://ror.org/04r12t513"
            },
            {
              "label": "Haikou City People's Hospital",
              "type": "related",
              "id": "https://ror.org/00ha5jx35"
            },
            {
              "label": "Second Xiangya Hospital of Central South University",
              "type": "related",
              "id": "https://ror.org/053v2gh09"
            },
            {
              "label": "Xiangya Hospital Central South University",
              "type": "related",
              "id": "https://ror.org/05c1yfj14"
            },
            {
              "label": "Zhuzhou Central Hospital",
              "type": "related",
              "id": "https://ror.org/03prq2784"
            }
          ],
          "domains": [
            "csu.edu.cn"
          ]
        },
        {
          "id": "https://openalex.org/I4210159865",
          "display_name": "Xiangya Hospital Central South University",
          "country": "China",
          "type": "healthcare",
          "ror_id": "https://ror.org/05c1yfj14",
          "status": "active",
          "types": [
            "funder",
            "healthcare"
          ],
          "established": 1906,
          "names": [
            {
              "lang": "en",
              "types": [
                "ror_display",
                "label"
              ],
              "value": "Xiangya Hospital Central South University"
            },
            {
              "lang": "zh",
              "types": [
                "label"
              ],
              "value": "中南大学湘雅医院"
            }
          ],
          "locations": [
            {
              "geonames_details": {
                "continent_code": "AS",
                "continent_name": "Asia",
                "country_code": "CN",
                "country_name": "China",
                "country_subdivision_code": "HN",
                "country_subdivision_name": "Hunan",
                "lat": 28.19874,
                "lng": 112.97087,
                "name": "Changsha"
              },
              "geonames_id": 1815577
            }
          ],
          "country_code": "CN",
          "city": "Changsha",
          "latitude": 28.19874,
          "longitude": 112.97087,
          "links": [
            {
              "type": "website",
              "value": "http://www.xiangya.com.cn/web/#"
            }
          ],
          "website": "http://www.xiangya.com.cn/web/#",
          "external_ids": [
            {
              "all": [
                "501100011790"
              ],
              "preferred": "501100011790",
              "type": "fundref"
            },
            {
              "all": [
                "grid.452223.0"
              ],
              "preferred": "grid.452223.0",
              "type": "grid"
            },
            {
              "all": [
                "0000 0004 1757 7615"
              ],
              "preferred": null,
              "type": "isni"
            }
          ],
          "fundref_id": "501100011790",
          "grid_id": "grid.452223.0",
          "relationships": [
            {
              "label": "Central South University",
              "type": "related",
              "id": "https://ror.org/00f1zfq44"
            }
          ],
          "domains": []
        }
      ],
      "position": "middle"
    },
    {
      "id": "https://openalex.org/A5100369038",
      "display_name": "Ning Li",
      "orcid": "https://orcid.org/0000-0002-6518-2541",
      "institutions": [
        {
          "id": "https://openalex.org/I139660479",
          "display_name": "Central South University",
          "country": "China",
          "type": "education",
          "ror_id": "https://ror.org/00f1zfq44",
          "status": "active",
          "types": [
            "education",
            "funder"
          ],
          "established": 2000,
          "names": [
            {
              "lang": null,
              "types": [
                "acronym"
              ],
              "value": "CSU"
            },
            {
              "lang": "en",
              "types": [
                "ror_display",
                "label"
              ],
              "value": "Central South University"
            },
            {
              "lang": "zh",
              "types": [
                "label"
              ],
              "value": "中南大学"
            }
          ],
          "locations": [
            {
              "geonames_details": {
                "continent_code": "AS",
                "continent_name": "Asia",
                "country_code": "CN",
                "country_name": "China",
                "country_subdivision_code": "HN",
                "country_subdivision_name": "Hunan",
                "lat": 28.19874,
                "lng": 112.97087,
                "name": "Changsha"
              },
              "geonames_id": 1815577
            }
          ],
          "country_code": "CN",
          "city": "Changsha",
          "latitude": 28.19874,
          "longitude": 112.97087,
          "links": [
            {
              "type": "website",
              "value": "https://www.csu.edu.cn"
            },
            {
              "type": "wikipedia",
              "value": "http://en.wikipedia.org/wiki/Central_South_University"
            }
          ],
          "website": "https://www.csu.edu.cn",
          "external_ids": [
            {
              "all": [
                "501100002822",
                "501100012476",
                "501100012486"
              ],
              "preferred": null,
              "type": "fundref"
            },
            {
              "all": [
                "grid.216417.7"
              ],
              "preferred": "grid.216417.7",
              "type": "grid"
            },
            {
              "all": [
                "0000 0001 0379 7164"
              ],
              "preferred": null,
              "type": "isni"
            },
            {
              "all": [
                "Q5061828"
              ],
              "preferred": null,
              "type": "wikidata"
            }
          ],
          "grid_id": "grid.216417.7",
          "relationships": [
            {
              "label": "State Key Laboratory of High Performance Complex Manufacturing",
              "type": "child",
              "id": "https://ror.org/04xjtqb36"
            },
            {
              "label": "State Key Laboratory of Powder Metallurgy",
              "type": "child",
              "id": "https://ror.org/04r12t513"
            },
            {
              "label": "Haikou City People's Hospital",
              "type": "related",
              "id": "https://ror.org/00ha5jx35"
            },
            {
              "label": "Second Xiangya Hospital of Central South University",
              "type": "related",
              "id": "https://ror.org/053v2gh09"
            },
            {
              "label": "Xiangya Hospital Central South University",
              "type": "related",
              "id": "https://ror.org/05c1yfj14"
            },
            {
              "label": "Zhuzhou Central Hospital",
              "type": "related",
              "id": "https://ror.org/03prq2784"
            }
          ],
          "domains": [
            "csu.edu.cn"
          ]
        },
        {
          "id": "https://openalex.org/I4210159865",
          "display_name": "Xiangya Hospital Central South University",
          "country": "China",
          "type": "healthcare",
          "ror_id": "https://ror.org/05c1yfj14",
          "status": "active",
          "types": [
            "funder",
            "healthcare"
          ],
          "established": 1906,
          "names": [
            {
              "lang": "en",
              "types": [
                "ror_display",
                "label"
              ],
              "value": "Xiangya Hospital Central South University"
            },
            {
              "lang": "zh",
              "types": [
                "label"
              ],
              "value": "中南大学湘雅医院"
            }
          ],
          "locations": [
            {
              "geonames_details": {
                "continent_code": "AS",
                "continent_name": "Asia",
                "country_code": "CN",
                "country_name": "China",
                "country_subdivision_code": "HN",
                "country_subdivision_name": "Hunan",
                "lat": 28.19874,
                "lng": 112.97087,
                "name": "Changsha"
              },
              "geonames_id": 1815577
            }
          ],
          "country_code": "CN",
          "city": "Changsha",
          "latitude": 28.19874,
          "longitude": 112.97087,
          "links": [
            {
              "type": "website",
              "value": "http://www.xiangya.com.cn/web/#"
            }
          ],
          "website": "http://www.xiangya.com.cn/web/#",
          "external_ids": [
            {
              "all": [
                "501100011790"
              ],
              "preferred": "501100011790",
              "type": "fundref"
            },
            {
              "all": [
                "grid.452223.0"
              ],
              "preferred": "grid.452223.0",
              "type": "grid"
            },
            {
              "all": [
                "0000 0004 1757 7615"
              ],
              "preferred": null,
              "type": "isni"
            }
          ],
          "fundref_id": "501100011790",
          "grid_id": "grid.452223.0",
          "relationships": [
            {
              "label": "Central South University",
              "type": "related",
              "id": "https://ror.org/00f1zfq44"
            }
          ],
          "domains": []
        }
      ],
      "position": "last"
    }
  ],
  "institutions": [
    {
      "id": "https://openalex.org/I139660479",
      "display_name": "Central South University",
      "country": "China",
      "type": "education",
      "ror_id": "https://ror.org/00f1zfq44",
      "status": "active",
      "types": [
        "education",
        "funder"
      ],
      "established": 2000,
      "names": [
        {
          "lang": null,
          "types": [
            "acronym"
          ],
          "value": "CSU"
        },
        {
          "lang": "en",
          "types": [
            "ror_display",
            "label"
          ],
          "value": "Central South University"
        },
        {
          "lang": "zh",
          "types": [
            "label"
          ],
          "value": "中南大学"
        }
      ],
      "locations": [
        {
          "geonames_details": {
            "continent_code": "AS",
            "continent_name": "Asia",
            "country_code": "CN",
            "country_name": "China",
            "country_subdivision_code": "HN",
            "country_subdivision_name": "Hunan",
            "lat": 28.19874,
            "lng": 112.97087,
            "name": "Changsha"
          },
          "geonames_id": 1815577
        }
      ],
      "country_code": "CN",
      "city": "Changsha",
      "latitude": 28.19874,
      "longitude": 112.97087,
      "links": [
        {
          "type": "website",
          "value": "https://www.csu.edu.cn"
        },
        {
          "type": "wikipedia",
          "value": "http://en.wikipedia.org/wiki/Central_South_University"
        }
      ],
      "website": "https://www.csu.edu.cn",
      "external_ids": [
        {
          "all": [
            "501100002822",
            "501100012476",
            "501100012486"
          ],
          "preferred": null,
          "type": "fundref"
        },
        {
          "all": [
            "grid.216417.7"
          ],
          "preferred": "grid.216417.7",
          "type": "grid"
        },
        {
          "all": [
            "0000 0001 0379 7164"
          ],
          "preferred": null,
          "type": "isni"
        },
        {
          "all": [
            "Q5061828"
          ],
          "preferred": null,
          "type": "wikidata"
        }
      ],
      "grid_id": "grid.216417.7",
      "relationships": [
        {
          "label": "State Key Laboratory of High Performance Complex Manufacturing",
          "type": "child",
          "id": "https://ror.org/04xjtqb36"
        },
        {
          "label": "State Key Laboratory of Powder Metallurgy",
          "type": "child",
          "id": "https://ror.org/04r12t513"
        },
        {
          "label": "Haikou City People's Hospital",
          "type": "related",
          "id": "https://ror.org/00ha5jx35"
        },
        {
          "label": "Second Xiangya Hospital of Central South University",
          "type": "related",
          "id": "https://ror.org/053v2gh09"
        },
        {
          "label": "Xiangya Hospital Central South University",
          "type": "related",
          "id": "https://ror.org/05c1yfj14"
        },
        {
          "label": "Zhuzhou Central Hospital",
          "type": "related",
          "id": "https://ror.org/03prq2784"
        }
      ],
      "domains": [
        "csu.edu.cn"
      ]
    },
    {
      "id": "https://openalex.org/I4210159865",
      "display_name": "Xiangya Hospital Central South University",
      "country": "China",
      "type": "healthcare",
      "ror_id": "https://ror.org/05c1yfj14",
      "status": "active",
      "types": [
        "funder",
        "healthcare"
      ],
      "established": 1906,
      "names": [
        {
          "lang": "en",
          "types": [
            "ror_display",
            "label"
          ],
          "value": "Xiangya Hospital Central South University"
        },
        {
          "lang": "zh",
          "types": [
            "label"
          ],
          "value": "中南大学湘雅医院"
        }
      ],
      "locations": [
        {
          "geonames_details": {
            "continent_code": "AS",
            "continent_name": "Asia",
            "country_code": "CN",
            "country_name": "China",
            "country_subdivision_code": "HN",
            "country_subdivision_name": "Hunan",
            "lat": 28.19874,
            "lng": 112.97087,
            "name": "Changsha"
          },
          "geonames_id": 1815577
        }
      ],
      "country_code": "CN",
      "city": "Changsha",
      "latitude": 28.19874,
      "longitude": 112.97087,
      "links": [
        {
          "type": "website",
          "value": "http://www.xiangya.com.cn/web/#"
        }
      ],
      "website": "http://www.xiangya.com.cn/web/#",
      "external_ids": [
        {
          "all": [
            "501100011790"
          ],
          "preferred": "501100011790",
          "type": "fundref"
        },
        {
          "all": [
            "grid.452223.0"
          ],
          "preferred": "grid.452223.0",
          "type": "grid"
        },
        {
          "all": [
            "0000 0004 1757 7615"
          ],
          "preferred": null,
          "type": "isni"
        }
      ],
      "fundref_id": "501100011790",
      "grid_id": "grid.452223.0",
      "relationships": [
        {
          "label": "Central South University",
          "type": "related",
          "id": "https://ror.org/00f1zfq44"
        }
      ],
      "domains": []
    },
    {
      "id": "https://openalex.org/I139660479",
      "display_name": "Central South University",
      "country": "China",
      "type": "education",
      "ror_id": "https://ror.org/00f1zfq44",
      "status": "active",
      "types": [
        "education",
        "funder"
      ],
      "established": 2000,
      "names": [
        {
          "lang": null,
          "types": [
            "acronym"
          ],
          "value": "CSU"
        },
        {
          "lang": "en",
          "types": [
            "ror_display",
            "label"
          ],
          "value": "Central South University"
        },
        {
          "lang": "zh",
          "types": [
            "label"
          ],
          "value": "中南大学"
        }
      ],
      "locations": [
        {
          "geonames_details": {
            "continent_code": "AS",
            "continent_name": "Asia",
            "country_code": "CN",
            "country_name": "China",
            "country_subdivision_code": "HN",
            "country_subdivision_name": "Hunan",
            "lat": 28.19874,
            "lng": 112.97087,
            "name": "Changsha"
          },
          "geonames_id": 1815577
        }
      ],
      "country_code": "CN",
      "city": "Changsha",
      "latitude": 28.19874,
      "longitude": 112.97087,
      "links": [
        {
          "type": "website",
          "value": "https://www.csu.edu.cn"
        },
        {
          "type": "wikipedia",
          "value": "http://en.wikipedia.org/wiki/Central_South_University"
        }
      ],
      "website": "https://www.csu.edu.cn",
      "external_ids": [
        {
          "all": [
            "501100002822",
            "501100012476",
            "501100012486"
          ],
          "preferred": null,
          "type": "fundref"
        },
        {
          "all": [
            "grid.216417.7"
          ],
          "preferred": "grid.216417.7",
          "type": "grid"
        },
        {
          "all": [
            "0000 0001 0379 7164"
          ],
          "preferred": null,
          "type": "isni"
        },
        {
          "all": [
            "Q5061828"
          ],
          "preferred": null,
          "type": "wikidata"
        }
      ],
      "grid_id": "grid.216417.7",
      "relationships": [
        {
          "label": "State Key Laboratory of High Performance Complex Manufacturing",
          "type": "child",
          "id": "https://ror.org/04xjtqb36"
        },
        {
          "label": "State Key Laboratory of Powder Metallurgy",
          "type": "child",
          "id": "https://ror.org/04r12t513"
        },
        {
          "label": "Haikou City People's Hospital",
          "type": "related",
          "id": "https://ror.org/00ha5jx35"
        },
        {
          "label": "Second Xiangya Hospital of Central South University",
          "type": "related",
          "id": "https://ror.org/053v2gh09"
        },
        {
          "label": "Xiangya Hospital Central South University",
          "type": "related",
          "id": "https://ror.org/05c1yfj14"
        },
        {
          "label": "Zhuzhou Central Hospital",
          "type": "related",
          "id": "https://ror.org/03prq2784"
        }
      ],
      "domains": [
        "csu.edu.cn"
      ]
    },
    {
      "id": "https://openalex.org/I4210159865",
      "display_name": "Xiangya Hospital Central South University",
      "country": "China",
      "type": "healthcare",
      "ror_id": "https://ror.org/05c1yfj14",
      "status": "active",
      "types": [
        "funder",
        "healthcare"
      ],
      "established": 1906,
      "names": [
        {
          "lang": "en",
          "types": [
            "ror_display",
            "label"
          ],
          "value": "Xiangya Hospital Central South University"
        },
        {
          "lang": "zh",
          "types": [
            "label"
          ],
          "value": "中南大学湘雅医院"
        }
      ],
      "locations": [
        {
          "geonames_details": {
            "continent_code": "AS",
            "continent_name": "Asia",
            "country_code": "CN",
            "country_name": "China",
            "country_subdivision_code": "HN",
            "country_subdivision_name": "Hunan",
            "lat": 28.19874,
            "lng": 112.97087,
            "name": "Changsha"
          },
          "geonames_id": 1815577
        }
      ],
      "country_code": "CN",
      "city": "Changsha",
      "latitude": 28.19874,
      "longitude": 112.97087,
      "links": [
        {
          "type": "website",
          "value": "http://www.xiangya.com.cn/web/#"
        }
      ],
      "website": "http://www.xiangya.com.cn/web/#",
      "external_ids": [
        {
          "all": [
            "501100011790"
          ],
          "preferred": "501100011790",
          "type": "fundref"
        },
        {
          "all": [
            "grid.452223.0"
          ],
          "preferred": "grid.452223.0",
          "type": "grid"
        },
        {
          "all": [
            "0000 0004 1757 7615"
          ],
          "preferred": null,
          "type": "isni"
        }
      ],
      "fundref_id": "501100011790",
      "grid_id": "grid.452223.0",
      "relationships": [
        {
          "label": "Central South University",
          "type": "related",
          "id": "https://ror.org/00f1zfq44"
        }
      ],
      "domains": []
    },
    {
      "id": "https://openalex.org/I139660479",
      "display_name": "Central South University",
      "country": "China",
      "type": "education",
      "ror_id": "https://ror.org/00f1zfq44",
      "status": "active",
      "types": [
        "education",
        "funder"
      ],
      "established": 2000,
      "names": [
        {
          "lang": null,
          "types": [
            "acronym"
          ],
          "value": "CSU"
        },
        {
          "lang": "en",
          "types": [
            "ror_display",
            "label"
          ],
          "value": "Central South University"
        },
        {
          "lang": "zh",
          "types": [
            "label"
          ],
          "value": "中南大学"
        }
      ],
      "locations": [
        {
          "geonames_details": {
            "continent_code": "AS",
            "continent_name": "Asia",
            "country_code": "CN",
            "country_name": "China",
            "country_subdivision_code": "HN",
            "country_subdivision_name": "Hunan",
            "lat": 28.19874,
            "lng": 112.97087,
            "name": "Changsha"
          },
          "geonames_id": 1815577
        }
      ],
      "country_code": "CN",
      "city": "Changsha",
      "latitude": 28.19874,
      "longitude": 112.97087,
      "links": [
        {
          "type": "website",
          "value": "https://www.csu.edu.cn"
        },
        {
          "type": "wikipedia",
          "value": "http://en.wikipedia.org/wiki/Central_South_University"
        }
      ],
      "website": "https://www.csu.edu.cn",
      "external_ids": [
        {
          "all": [
            "501100002822",
            "501100012476",
            "501100012486"
          ],
          "preferred": null,
          "type": "fundref"
        },
        {
          "all": [
            "grid.216417.7"
          ],
          "preferred": "grid.216417.7",
          "type": "grid"
        },
        {
          "all": [
            "0000 0001 0379 7164"
          ],
          "preferred": null,
          "type": "isni"
        },
        {
          "all": [
            "Q5061828"
          ],
          "preferred": null,
          "type": "wikidata"
        }
      ],
      "grid_id": "grid.216417.7",
      "relationships": [
        {
          "label": "State Key Laboratory of High Performance Complex Manufacturing",
          "type": "child",
          "id": "https://ror.org/04xjtqb36"
        },
        {
          "label": "State Key Laboratory of Powder Metallurgy",
          "type": "child",
          "id": "https://ror.org/04r12t513"
        },
        {
          "label": "Haikou City People's Hospital",
          "type": "related",
          "id": "https://ror.org/00ha5jx35"
        },
        {
          "label": "Second Xiangya Hospital of Central South University",
          "type": "related",
          "id": "https://ror.org/053v2gh09"
        },
        {
          "label": "Xiangya Hospital Central South University",
          "type": "related",
          "id": "https://ror.org/05c1yfj14"
        },
        {
          "label": "Zhuzhou Central Hospital",
          "type": "related",
          "id": "https://ror.org/03prq2784"
        }
      ],
      "domains": [
        "csu.edu.cn"
      ]
    },
    {
      "id": "https://openalex.org/I4210159865",
      "display_name": "Xiangya Hospital Central South University",
      "country": "China",
      "type": "healthcare",
      "ror_id": "https://ror.org/05c1yfj14",
      "status": "active",
      "types": [
        "funder",
        "healthcare"
      ],
      "established": 1906,
      "names": [
        {
          "lang": "en",
          "types": [
            "ror_display",
            "label"
          ],
          "value": "Xiangya Hospital Central South University"
        },
        {
          "lang": "zh",
          "types": [
            "label"
          ],
          "value": "中南大学湘雅医院"
        }
      ],
      "locations": [
        {
          "geonames_details": {
            "continent_code": "AS",
            "continent_name": "Asia",
            "country_code": "CN",
            "country_name": "China",
            "country_subdivision_code": "HN",
            "country_subdivision_name": "Hunan",
            "lat": 28.19874,
            "lng": 112.97087,
            "name": "Changsha"
          },
          "geonames_id": 1815577
        }
      ],
      "country_code": "CN",
      "city": "Changsha",
      "latitude": 28.19874,
      "longitude": 112.97087,
      "links": [
        {
          "type": "website",
          "value": "http://www.xiangya.com.cn/web/#"
        }
      ],
      "website": "http://www.xiangya.com.cn/web/#",
      "external_ids": [
        {
          "all": [
            "501100011790"
          ],
          "preferred": "501100011790",
          "type": "fundref"
        },
        {
          "all": [
            "grid.452223.0"
          ],
          "preferred": "grid.452223.0",
          "type": "grid"
        },
        {
          "all": [
            "0000 0004 1757 7615"
          ],
          "preferred": null,
          "type": "isni"
        }
      ],
      "fundref_id": "501100011790",
      "grid_id": "grid.452223.0",
      "relationships": [
        {
          "label": "Central South University",
          "type": "related",
          "id": "https://ror.org/00f1zfq44"
        }
      ],
      "domains": []
    }
  ],
  "topics": [
    {
      "id": "https://openalex.org/T10158",
      "display_name": "Cancer Immunotherapy and Biomarkers",
      "score": 0.9993000030517578
    },
    {
      "id": "https://openalex.org/T11491",
      "display_name": "CAR-T cell therapy research",
      "score": 0.9991999864578247
    },
    {
      "id": "https://openalex.org/T10613",
      "display_name": "Virus-based gene therapy research",
      "score": 0.9984999895095825
    }
  ],
  "venue": {
    "id": "https://openalex.org/S2739142469",
    "display_name": "Signal Transduction and Targeted Therapy",
    "issn": [
      "2059-3635",
      "2095-9907"
    ],
    "type": "journal",
    "is_oa": true
  },
  "biblio": {
    "volume": "10",
    "issue": "1",
    "first_page": "227",
    "last_page": "227"
  },
  "doi": "https://doi.org/10.1038/s41392-025-02280-1",
  "ids": {
    "openalex": "https://openalex.org/W4412745982",
    "doi": "https://doi.org/10.1038/s41392-025-02280-1",
    "pmid": "https://pubmed.ncbi.nlm.nih.gov/40739089"
  },
  "abstract_inverted_index": {
    "Abstract": [
      0
    ],
    "Immune": [
      1
    ],
    "evasion": [
      2,
      104
    ],
    "represents": [
      3
    ],
    "a": [
      4,
      45
    ],
    "significant": [
      5
    ],
    "challenge": [
      6
    ],
    "in": [
      7,
      80,
      207,
      216,
      225
    ],
    "oncology.": [
      8
    ],
    "It": [
      9,
      41
    ],
    "allows": [
      10
    ],
    "tumors": [
      11,
      51
    ],
    "to": [
      12,
      24,
      34,
      43,
      52,
      156,
      160,
      183,
      219
    ],
    "evade": [
      13,
      38
    ],
    "immune": [
      14,
      39,
      54,
      59,
      61,
      82,
      92,
      103,
      161,
      167
    ],
    "surveillance": [
      15
    ],
    "and": [
      16,
      22,
      64,
      66,
      84,
      105,
      146,
      177,
      191,
      201,
      223,
      231
    ],
    "destruction,": [
      17
    ],
    "thereby": [
      18
    ],
    "complicating": [
      19
    ],
    "therapeutic": [
      20,
      185,
      193
    ],
    "interventions": [
      21
    ],
    "contributing": [
      23
    ],
    "suboptimal": [
      25
    ],
    "patient": [
      26,
      229
    ],
    "outcomes.": [
      27
    ],
    "This": [
      28
    ],
    "review": [
      29,
      96,
      170,
      214
    ],
    "addresses": [
      30
    ],
    "the": [
      31,
      72,
      76,
      86,
      107,
      164,
      172,
      178
    ],
    "critical": [
      32
    ],
    "need": [
      33
    ],
    "understand": [
      35
    ],
    "how": [
      36,
      99
    ],
    "cancers": [
      37
    ],
    "surveillance.": [
      40
    ],
    "aims": [
      42
    ],
    "provide": [
      44
    ],
    "comprehensive": [
      46
    ],
    "overview": [
      47
    ],
    "of": [
      48,
      50,
      75,
      88,
      109,
      114,
      141,
      150,
      166,
      174,
      180,
      212,
      235
    ],
    "strategies": [
      49
    ],
    "escape": [
      53
    ],
    "detection": [
      55
    ],
    "by": [
      56
    ],
    "examining": [
      57
    ],
    "tumor-induced": [
      58
    ],
    "suppression,": [
      60
    ],
    "checkpoint": [
      62
    ],
    "regulation,": [
      63
    ],
    "genetic": [
      65
    ],
    "epigenetic": [
      67
    ],
    "influences.": [
      68
    ],
    "Moreover,": [
      69
    ],
    "it": [
      70,
      188
    ],
    "explores": [
      71
    ],
    "dynamic": [
      73
    ],
    "role": [
      74,
      113
    ],
    "tumor": [
      77,
      100
    ],
    "microenvironment": [
      78
    ],
    "(TME)": [
      79
    ],
    "fostering": [
      81
    ],
    "resistance": [
      83
    ],
    "highlights": [
      85
    ],
    "impact": [
      87
    ],
    "metabolic": [
      89
    ],
    "reprogramming": [
      90
    ],
    "on": [
      91,
      98
    ],
    "suppression.": [
      93
    ],
    "Additionally,": [
      94
    ],
    "this": [
      95,
      169,
      213
    ],
    "focuses": [
      97
    ],
    "heterogeneity": [
      101
    ],
    "influences": [
      102
    ],
    "discusses": [
      106,
      189
    ],
    "limitations": [
      108
    ],
    "current": [
      110
    ],
    "immunotherapies.": [
      111
    ],
    "The": [
      112,
      210
    ],
    "key": [
      115
    ],
    "signaling": [
      116
    ],
    "pathways,": [
      117
    ],
    "including": [
      118
    ],
    "programmed": [
      119
    ],
    "cell": [
      120,
      124
    ],
    "death": [
      121,
      125
    ],
    "protein": [
      122
    ],
    "1/programmed": [
      123
    ],
    "ligand": [
      126
    ],
    "1": [
      127
    ],
    "(PD-1/PD-L1),": [
      128
    ],
    "cytotoxic": [
      129
    ],
    "T-lymphocyte–associated": [
      130
    ],
    "antigen": [
      131
    ],
    "4": [
      132
    ],
    "(CTLA-4),": [
      133
    ],
    "transforming": [
      134
    ],
    "growth": [
      135
    ],
    "factor-β": [
      136
    ],
    "(TGF-β),": [
      137
    ],
    "nuclear": [
      138
    ],
    "factor": [
      139
    ],
    "kappa-light-chain-enhancer": [
      140
    ],
    "activated": [
      142
    ],
    "B": [
      143
    ],
    "cells": [
      144
    ],
    "(NF-κB),": [
      145
    ],
    "cyclic": [
      147
    ],
    "GMP-AMP": [
      148
    ],
    "synthase-stimulator": [
      149
    ],
    "interferon": [
      151
    ],
    "genes": [
      152
    ],
    "(cGAS–STING)": [
      153
    ],
    "is": [
      154
    ],
    "analyzed": [
      155
    ],
    "elucidate": [
      157
    ],
    "their": [
      158
    ],
    "contributions": [
      159
    ],
    "escape.": [
      162
    ],
    "Emphasizing": [
      163
    ],
    "complexities": [
      165
    ],
    "evasion,": [
      168
    ],
    "underscores": [
      171
    ],
    "importance": [
      173
    ],
    "personalized": [
      175
    ],
    "approaches": [
      176
    ],
    "integration": [
      179
    ],
    "multi-omics": [
      181
    ],
    "data": [
      182
    ],
    "combat": [
      184
    ],
    "resistance.": [
      186
    ],
    "Furthermore,": [
      187
    ],
    "novel": [
      190
    ],
    "emerging": [
      192
    ],
    "strategies,": [
      194
    ],
    "such": [
      195
    ],
    "as": [
      196
    ],
    "bispecific": [
      197
    ],
    "antibodies,": [
      198
    ],
    "oncolytic": [
      199
    ],
    "viruses,": [
      200
    ],
    "nanotechnology-driven": [
      202
    ],
    "immunotherapies,": [
      203
    ],
    "showcasing": [
      204
    ],
    "innovative": [
      205
    ],
    "avenues": [
      206
    ],
    "cancer": [
      208,
      236
    ],
    "treatment.": [
      209
    ],
    "significance": [
      211
    ],
    "lies": [
      215
    ],
    "its": [
      217
    ],
    "potential": [
      218
    ],
    "guide": [
      220
    ],
    "future": [
      221
    ],
    "research": [
      222
    ],
    "innovations": [
      224
    ],
    "immunotherapy,": [
      226
    ],
    "ultimately": [
      227
    ],
    "improving": [
      228
    ],
    "outcomes": [
      230
    ],
    "advancing": [
      232
    ],
    "our": [
      233
    ],
    "understanding": [
      234
    ],
    "immunology.": [
      237
    ]
  },
  "referenced_works_count": 651,
  "related_works": [
    "https://openalex.org/W2912064558",
    "https://openalex.org/W4316927247",
    "https://openalex.org/W2789344762",
    "https://openalex.org/W3128318804",
    "https://openalex.org/W4388112172",
    "https://openalex.org/W38803104",
    "https://openalex.org/W2783288907",
    "https://openalex.org/W2902626376",
    "https://openalex.org/W3095731313",
    "https://openalex.org/W4410076710"
  ]
}